lucidCameraGui/lucidLiveStream.py
lucidCameraGui/lucidStreamGui.py
lucidCameraGUI-1.1.dist-info/METADATA
lucidCameraGUI-1.1.dist-info/WHEEL
lucidCameraGUI-1.1.dist-info/entry_points.txt
lucidCameraGUI-1.1.dist-info/top_level.txt
lucidCameraGUI-1.1.dist-info/RECORD
