Metadata-Version: 2.1
Name: lucidCameraGUI
Version: 1.1
Summary: A GUI for running a LucidVision camera
Author-email: "Kenneth P. Marshall" <kenneth.marshall@esrf.fr>
Maintainer-email: "Kenneth P. Marshall" <kenneth.marshall@esrf.fr>
Project-URL: repository, https://github.com/msujas/lucidCameraGui
Keywords: Lucid Vision,ArenaView,gui
Classifier: Development Status :: 4 - Beta
Classifier: Programming Language :: Python :: 3.8
Classifier: Programming Language :: Python :: 3.9
Classifier: Programming Language :: Python :: 3.10
Classifier: Programming Language :: Python :: 3.11
Classifier: Programming Language :: Python :: 3.12
Requires-Python: >=3.8
Requires-Dist: opencv-python
Requires-Dist: numpy
Requires-Dist: PyQt5
